ubox/__init__.py
ubox/crypto.py
ubox/identifiers.py
ubox/random.py
ubox-0.0.1.5.dist-info/LICENSE
ubox-0.0.1.5.dist-info/METADATA
ubox-0.0.1.5.dist-info/WHEEL
ubox-0.0.1.5.dist-info/top_level.txt
ubox-0.0.1.5.dist-info/RECORD
