Metadata-Version: 2.1
Name: ubox
Version: 0.0.1.5
Summary: Python Utils Box for Botting/Spoofing (encryption, random, etc)
Author: Tekky
Author-email: <support@g4f.ai>
Classifier: Development Status :: 2 - Pre-Alpha
Classifier: Intended Audience :: Developers
Classifier: Programming Language :: Python :: 3
Classifier: Operating System :: Unix
Classifier: Operating System :: MacOS :: MacOS X
Classifier: Operating System :: Microsoft :: Windows
License-File: LICENSE
